mkdocs_plugin_progress/__init__.py
mkdocs_plugin_progress-1.2.0.dist-info/LICENSE
mkdocs_plugin_progress-1.2.0.dist-info/METADATA
mkdocs_plugin_progress-1.2.0.dist-info/WHEEL
mkdocs_plugin_progress-1.2.0.dist-info/entry_points.txt
mkdocs_plugin_progress-1.2.0.dist-info/top_level.txt
mkdocs_plugin_progress-1.2.0.dist-info/RECORD
