Metadata-Version: 2.1
Name: mkdocs-plugin-progress
Version: 1.2.0
Summary: A plugin for MkDocs that lets you know exactly what is happening during the build.
Home-page: https://github.com/rdilweb/mkdocs-plugin-progress
Author: Reece Dunham
Author-email: me@rdil.rocks
License: Apache 2
Project-URL: Bug Tracker, https://github.com/rdilweb/mkdocs-plugin-progress/issues
Project-URL: Source Code, https://github.com/rdilweb/mkdocs-plugin-progress
Project-URL: License, https://github.com/rdilweb/mkdocs-plugin-progress/blob/master/LICENSE
Keywords: mkdocs,plugin,progress,build,debugging
Platform: UNKNOWN
Requires-Python: >=3.3
Requires-Dist: mkdocs (>=1.0.0)
